[
    {
        "%vlocity_namespace%__DisplayType__c": "REFERENCE",
        "%vlocity_namespace%__DomainObjectAPIName__c": "Turbo Extract",
        "%vlocity_namespace%__DomainObjectCreationOrder__c": 0,
        "%vlocity_namespace%__DomainObjectFieldAPIName__c": "orchItem",
        "%vlocity_namespace%__FilterGroup__c": 0,
        "%vlocity_namespace%__FilterOperator__c": "=",
        "%vlocity_namespace%__FilterValue__c": "orderId",
        "%vlocity_namespace%__GlobalKey__c": "29cd136a-90f1-34d1-8be2-0529c7c0b783",
        "%vlocity_namespace%__InterfaceFieldAPIName__c": "%vlocity_namespace%__OrchestrationPlanId__r.%vlocity_namespace%__OrderId__c",
        "%vlocity_namespace%__InterfaceObjectLookupOrder__c": 1,
        "%vlocity_namespace%__InterfaceObjectName__c": "%vlocity_namespace%__OrchestrationItem__c",
        "%vlocity_namespace%__IsDisabled__c": false,
        "%vlocity_namespace%__IsRequiredForUpsert__c": false,
        "%vlocity_namespace%__MapId__c": "valGetFirstOrchestrationItemFailedCustoma1f76000000WGwBAAWItem0",
        "%vlocity_namespace%__OMplusSyncEnabled__c": true,
        "%vlocity_namespace%__UpsertKey__c": false,
        "Name": "valGetFirstOrchestrationItemFailed",
        "VlocityDataPackType": "SObject",
        "VlocityRecordSObjectType": "%vlocity_namespace%__DRMapItem__c"
    },
    {
        "%vlocity_namespace%__DisplayType__c": "PICKLIST",
        "%vlocity_namespace%__DomainObjectAPIName__c": "Turbo Extract",
        "%vlocity_namespace%__DomainObjectCreationOrder__c": 0,
        "%vlocity_namespace%__DomainObjectFieldAPIName__c": "orchItem",
        "%vlocity_namespace%__FilterGroup__c": 0,
        "%vlocity_namespace%__FilterOperator__c": "IN",
        "%vlocity_namespace%__FilterValue__c": "statusFailed:status",
        "%vlocity_namespace%__GlobalKey__c": "ebf2c98c-d10f-6061-1d45-8cb32752eb5a",
        "%vlocity_namespace%__InterfaceFieldAPIName__c": "%vlocity_namespace%__State__c",
        "%vlocity_namespace%__InterfaceObjectLookupOrder__c": 1,
        "%vlocity_namespace%__InterfaceObjectName__c": "%vlocity_namespace%__OrchestrationItem__c",
        "%vlocity_namespace%__IsDisabled__c": false,
        "%vlocity_namespace%__IsRequiredForUpsert__c": false,
        "%vlocity_namespace%__MapId__c": "valGetFirstOrchestrationItemFailedCustoma1f76000000WGwBAAWItem1",
        "%vlocity_namespace%__OMplusSyncEnabled__c": true,
        "%vlocity_namespace%__UpsertKey__c": false,
        "Name": "valGetFirstOrchestrationItemFailed",
        "VlocityDataPackType": "SObject",
        "VlocityRecordSObjectType": "%vlocity_namespace%__DRMapItem__c"
    },
    {
        "%vlocity_namespace%__DomainObjectAPIName__c": "Turbo Extract",
        "%vlocity_namespace%__DomainObjectCreationOrder__c": 0,
        "%vlocity_namespace%__DomainObjectFieldAPIName__c": "orchItem",
        "%vlocity_namespace%__FilterGroup__c": 0,
        "%vlocity_namespace%__FilterOperator__c": "LIMIT",
        "%vlocity_namespace%__FilterValue__c": "1",
        "%vlocity_namespace%__GlobalKey__c": "1c2891ec-7ed9-8f43-49b2-ed8fec9ace18",
        "%vlocity_namespace%__InterfaceObjectLookupOrder__c": 1,
        "%vlocity_namespace%__InterfaceObjectName__c": "%vlocity_namespace%__OrchestrationItem__c",
        "%vlocity_namespace%__IsDisabled__c": false,
        "%vlocity_namespace%__IsRequiredForUpsert__c": false,
        "%vlocity_namespace%__MapId__c": "valGetFirstOrchestrationItemFailedCustoma1f76000000WGwBAAWItem2",
        "%vlocity_namespace%__OMplusSyncEnabled__c": true,
        "%vlocity_namespace%__UpsertKey__c": false,
        "Name": "valGetFirstOrchestrationItemFailed",
        "VlocityDataPackType": "SObject",
        "VlocityRecordSObjectType": "%vlocity_namespace%__DRMapItem__c"
    },
    {
        "%vlocity_namespace%__DomainObjectAPIName__c": "Turbo Extract",
        "%vlocity_namespace%__DomainObjectCreationOrder__c": 0,
        "%vlocity_namespace%__DomainObjectFieldAPIName__c": "orchItem",
        "%vlocity_namespace%__FilterGroup__c": 0,
        "%vlocity_namespace%__FilterOperator__c": "ORDER BY",
        "%vlocity_namespace%__FilterValue__c": "%vlocity_namespace%__TimestampReady__c DESC",
        "%vlocity_namespace%__GlobalKey__c": "a8543f73-b5de-44fc-caae-514aa2863e58",
        "%vlocity_namespace%__InterfaceObjectLookupOrder__c": 1,
        "%vlocity_namespace%__InterfaceObjectName__c": "%vlocity_namespace%__OrchestrationItem__c",
        "%vlocity_namespace%__IsDisabled__c": false,
        "%vlocity_namespace%__IsRequiredForUpsert__c": false,
        "%vlocity_namespace%__MapId__c": "valGetFirstOrchestrationItemFailedCustoma1f76000000WGwBAAWItem3",
        "%vlocity_namespace%__OMplusSyncEnabled__c": true,
        "%vlocity_namespace%__UpsertKey__c": false,
        "Name": "valGetFirstOrchestrationItemFailed",
        "VlocityDataPackType": "SObject",
        "VlocityRecordSObjectType": "%vlocity_namespace%__DRMapItem__c"
    },
    {
        "%vlocity_namespace%__DomainObjectAPIName__c": "Turbo Extract",
        "%vlocity_namespace%__DomainObjectCreationOrder__c": 1,
        "%vlocity_namespace%__DomainObjectFieldAPIName__c": "orchItem",
        "%vlocity_namespace%__GlobalKey__c": "32fa2bef-31bd-b59b-1635-70524277eb08",
        "%vlocity_namespace%__InterfaceFieldAPIName__c": "%vlocity_namespace%__State__c",
        "%vlocity_namespace%__InterfaceObjectName__c": "%vlocity_namespace%__OrchestrationItem__c",
        "%vlocity_namespace%__IsDisabled__c": false,
        "%vlocity_namespace%__IsRequiredForUpsert__c": false,
        "%vlocity_namespace%__MapId__c": "valGetFirstOrchestrationItemFailedCustoma1f76000000WGwBAAWItem4",
        "%vlocity_namespace%__OMplusSyncEnabled__c": true,
        "%vlocity_namespace%__UpsertKey__c": false,
        "Name": "valGetFirstOrchestrationItemFailed",
        "VlocityDataPackType": "SObject",
        "VlocityRecordSObjectType": "%vlocity_namespace%__DRMapItem__c"
    },
    {
        "%vlocity_namespace%__DomainObjectAPIName__c": "Turbo Extract",
        "%vlocity_namespace%__DomainObjectCreationOrder__c": 1,
        "%vlocity_namespace%__DomainObjectFieldAPIName__c": "orchItem",
        "%vlocity_namespace%__GlobalKey__c": "8f6e3356-acf8-1d62-038b-28b2024dc1f0",
        "%vlocity_namespace%__InterfaceFieldAPIName__c": "Name",
        "%vlocity_namespace%__InterfaceObjectName__c": "%vlocity_namespace%__OrchestrationItem__c",
        "%vlocity_namespace%__IsDisabled__c": false,
        "%vlocity_namespace%__IsRequiredForUpsert__c": false,
        "%vlocity_namespace%__MapId__c": "valGetFirstOrchestrationItemFailedCustoma1f76000000WGwBAAWItem5",
        "%vlocity_namespace%__OMplusSyncEnabled__c": true,
        "%vlocity_namespace%__UpsertKey__c": false,
        "Name": "valGetFirstOrchestrationItemFailed",
        "VlocityDataPackType": "SObject",
        "VlocityRecordSObjectType": "%vlocity_namespace%__DRMapItem__c"
    }
]