{
    "Active": true,
    "CaseOpening": [
        "GRUPO DE ABERTURA - FRAUDE",
        "GRUPO DE ABERTURA - GT UNIFICADO",
        "GRUPO DE ABERTURA - SOLUÇÃO ONLINE",
        "GRUPO DE ABERTURA - RESGATE DE GRAVAÇÃO"
    ],
    "Channel": "LOJAS PRÓPRIAS",
    "CustomerType": "CLIENTE",
    "LineType": [
        {
            "Plataform": "None"
        },
        {
            "Plataform": "PRÉ-PAGO GSM"
        },
        {
            "Plataform": "CONTROLE GSM"
        }
    ],
    "ProductType": "Pre",
    "Segmentation": "NÃO CLASSIFICADO",
    "ServiceTree": "Store",
    "VisibleTo": "ORG VIVO - B2C"
}